fabric_gunicorn.py
setup.py
fabric_gunicorn.egg-info/PKG-INFO
fabric_gunicorn.egg-info/SOURCES.txt
fabric_gunicorn.egg-info/dependency_links.txt
fabric_gunicorn.egg-info/requires.txt
fabric_gunicorn.egg-info/top_level.txt