Metadata-Version: 1.0
Name: fabric-gunicorn
Version: 0.1
Summary: fabric file with tasks to control a gunicorn process
Home-page: http://github.com/jarus/fabric-gunicorn
Author: Christoph Heer
Author-email: Christoph.Heer@googlemail.com
License: BSD
Platform: UNKNOWN
Classifier: Development Status :: 4 - Beta
Classifier: Intended Audience :: Developers
Classifier: License :: OSI Approved :: BSD License
Classifier: Operating System :: OS Independent
Classifier: Programming Language :: Python
Classifier: Topic :: Software Development :: Libraries :: Python Modules
